{
  "hash": "a7877e599",
  "author": "Haroen Viaene",
  "subject": "Feat(refinementList): add widget (algolia/vue-instantsearch#467)",
  "body": "* docs(refinementlist): initial\r\n\r\n* docs: add options\r\n\r\n* feat: add placeholder files\r\n\r\n* chore: connector optional\r\n\r\n* chore(SearchBox): refactor into real component & controlled\r\n\r\n* chore: add RefinementList to IS\r\n\r\n* feat(RefinementList): rendering\r\n\r\n* Update V2_PROGRESS.md\r\n\r\n* chore: remove old docs\r\n\r\n* docs: consistent OR\r\n\r\n* feat: search highlighting & some more\r\n\r\n* docs: add customisation stories\r\n\r\n* test\r\n\r\n* docs(transformItems): consistency\r\n\r\n* chore: move searchInput to v-model\r\n\r\n* fix: use correct this\r\n\r\n* fix: pass noop to toggleShowMore\r\n\r\n* feat: type for `sortBy`\r\n\r\n* chore: don't pass showMore on\r\n\r\n* chore: add & document more slots\r\n\r\n* chore: inline v-if & else\r\n\r\n* chore: pass disabled to showMore\r\n\r\n* fix: correct slotty and showMore goodness\r\n\r\n* chore: use correct state prop\r\n\r\n* docs: add classes\r\n\r\n* fix(types): just comma, not |\r\n\r\n* chore: fix import\r\n\r\n* fix(searchable): reset query on refine\r\n\r\n* chore(searchbox): have fallback for query\r\n\r\n* feat(highlighting): add _highlightResult to the item\r\n\r\nThis way it's usable as the content for the RFL\r\n\r\n* chore: easier syntax\r\n\r\n* feat: add no results slot\r\n\r\n* feat: no-refinement\r\n\r\n* chore: update tests\r\n\r\n* fix(component): merge conflict resolution\r\n\r\n* chore: fix linting\r\n\r\n* fix: correct type for `operator`\r\n\r\n* fix(rollup): make sure there's no invalid syntax in replacements\r\n\r\n* chore(rollup): don't transform process.env on esm/cjs because users do that on their end\r\n\r\n* chore: add panel & fix --noRefinement",
  "date": 1535651971,
  "longHash": "a7877e599726a3c0875a028fef62c33de9306061"
}
