[
  {
    "author_association": "CONTRIBUTOR",
    "body": "Which links are 404ing? \r\n\r\nthe documentation of conenctAutocomplete are here: https://community.algolia.com/instantsearch.js/v2/connectors/connectAutocomplete.html\r\n\r\nThe way to use it would be just like this guide: https://community.algolia.com/angular-instantsearch/guides/customize-widgets.html\r\n\r\nbut instead with a component that does the visual display of a dropdown list (like https://material.angular.io/components/autocomplete/overview)",
    "created_at": "2018-11-21T13:07:53Z",
    "html_url": "https://github.com/algolia/instantsearch/issues/3307#issuecomment-440656120",
    "id": 440656120,
    "issue_url": "https://api.github.com/repos/algolia/instantsearch/issues/3307",
    "node_id": "MDEyOklzc3VlQ29tbWVudDQ0MDY1NjEyMA==",
    "performed_via_github_app": null,
    "pin": null,
    "reactions": {
      "+1": 0,
      "-1": 0,
      "confused": 0,
      "eyes": 0,
      "heart": 0,
      "hooray": 0,
      "laugh": 0,
      "rocket": 0,
      "total_count": 0,
      "url": "https://api.github.com/repos/algolia/instantsearch/issues/comments/440656120/reactions"
    },
    "updated_at": "2018-11-21T13:07:53Z",
    "url": "https://api.github.com/repos/algolia/instantsearch/issues/comments/440656120",
    "user": {
      "avatar_url": "https://avatars.githubusercontent.com/u/6270048?v=4",
      "events_url": "https://api.github.com/users/Haroenv/events{/privacy}",
      "followers_url": "https://api.github.com/users/Haroenv/followers",
      "following_url": "https://api.github.com/users/Haroenv/following{/other_user}",
      "gists_url": "https://api.github.com/users/Haroenv/gists{/gist_id}",
      "gravatar_id": "",
      "html_url": "https://github.com/Haroenv",
      "id": 6270048,
      "login": "Haroenv",
      "node_id": "MDQ6VXNlcjYyNzAwNDg=",
      "organizations_url": "https://api.github.com/users/Haroenv/orgs",
      "received_events_url": "https://api.github.com/users/Haroenv/received_events",
      "repos_url": "https://api.github.com/users/Haroenv/repos",
      "site_admin": false,
      "starred_url": "https://api.github.com/users/Haroenv/starred{/owner}{/repo}",
      "subscriptions_url": "https://api.github.com/users/Haroenv/subscriptions",
      "type": "User",
      "url": "https://api.github.com/users/Haroenv",
      "user_view_type": "public"
    }
  },
  {
    "author_association": "NONE",
    "body": "@Haroenv \r\n\r\nAbout the broken links:\r\n\r\nhere: https://github.com/algolia/instantsearch.js/blob/c18e170333b8f557d542c7c383c9c09464c71607/src/connectors/autocomplete/connectAutocomplete.js#L16\r\n\r\nhere: https://github.com/algolia/instantsearch.js/blob/c18e170333b8f557d542c7c383c9c09464c71607/src/connectors/autocomplete/connectAutocomplete.js#L47\r\n\r\nthe first link here: https://community.algolia.com/instantsearch.js/v2/connectors/connectAutocomplete.html",
    "created_at": "2018-11-26T11:51:58Z",
    "html_url": "https://github.com/algolia/instantsearch/issues/3307#issuecomment-441613078",
    "id": 441613078,
    "issue_url": "https://api.github.com/repos/algolia/instantsearch/issues/3307",
    "node_id": "MDEyOklzc3VlQ29tbWVudDQ0MTYxMzA3OA==",
    "performed_via_github_app": null,
    "pin": null,
    "reactions": {
      "+1": 0,
      "-1": 0,
      "confused": 0,
      "eyes": 0,
      "heart": 0,
      "hooray": 0,
      "laugh": 0,
      "rocket": 0,
      "total_count": 0,
      "url": "https://api.github.com/repos/algolia/instantsearch/issues/comments/441613078/reactions"
    },
    "updated_at": "2018-11-26T11:51:58Z",
    "url": "https://api.github.com/repos/algolia/instantsearch/issues/comments/441613078",
    "user": {
      "avatar_url": "https://avatars.githubusercontent.com/u/4660731?v=4",
      "events_url": "https://api.github.com/users/corentin-gautier/events{/privacy}",
      "followers_url": "https://api.github.com/users/corentin-gautier/followers",
      "following_url": "https://api.github.com/users/corentin-gautier/following{/other_user}",
      "gists_url": "https://api.github.com/users/corentin-gautier/gists{/gist_id}",
      "gravatar_id": "",
      "html_url": "https://github.com/corentin-gautier",
      "id": 4660731,
      "login": "corentin-gautier",
      "node_id": "MDQ6VXNlcjQ2NjA3MzE=",
      "organizations_url": "https://api.github.com/users/corentin-gautier/orgs",
      "received_events_url": "https://api.github.com/users/corentin-gautier/received_events",
      "repos_url": "https://api.github.com/users/corentin-gautier/repos",
      "site_admin": false,
      "starred_url": "https://api.github.com/users/corentin-gautier/starred{/owner}{/repo}",
      "subscriptions_url": "https://api.github.com/users/corentin-gautier/subscriptions",
      "type": "User",
      "url": "https://api.github.com/users/corentin-gautier",
      "user_view_type": "public"
    }
  },
  {
    "author_association": "CONTRIBUTOR",
    "body": "I think that the second link now refers to: https://github.com/algolia/instantsearch.js/blob/a3821cf44ef72b7fcc806b9e3a457da4d72fd83f/dev/app/jquery/stories/autocomplete.stories.js.",
    "created_at": "2018-11-26T16:26:58Z",
    "html_url": "https://github.com/algolia/instantsearch/issues/3307#issuecomment-441703098",
    "id": 441703098,
    "issue_url": "https://api.github.com/repos/algolia/instantsearch/issues/3307",
    "node_id": "MDEyOklzc3VlQ29tbWVudDQ0MTcwMzA5OA==",
    "performed_via_github_app": null,
    "pin": null,
    "reactions": {
      "+1": 0,
      "-1": 0,
      "confused": 0,
      "eyes": 0,
      "heart": 0,
      "hooray": 0,
      "laugh": 0,
      "rocket": 0,
      "total_count": 0,
      "url": "https://api.github.com/repos/algolia/instantsearch/issues/comments/441703098/reactions"
    },
    "updated_at": "2018-11-26T16:26:58Z",
    "url": "https://api.github.com/repos/algolia/instantsearch/issues/comments/441703098",
    "user": {
      "avatar_url": "https://avatars.githubusercontent.com/u/6137112?v=4",
      "events_url": "https://api.github.com/users/francoischalifour/events{/privacy}",
      "followers_url": "https://api.github.com/users/francoischalifour/followers",
      "following_url": "https://api.github.com/users/francoischalifour/following{/other_user}",
      "gists_url": "https://api.github.com/users/francoischalifour/gists{/gist_id}",
      "gravatar_id": "",
      "html_url": "https://github.com/francoischalifour",
      "id": 6137112,
      "login": "francoischalifour",
      "node_id": "MDQ6VXNlcjYxMzcxMTI=",
      "organizations_url": "https://api.github.com/users/francoischalifour/orgs",
      "received_events_url": "https://api.github.com/users/francoischalifour/received_events",
      "repos_url": "https://api.github.com/users/francoischalifour/repos",
      "site_admin": false,
      "starred_url": "https://api.github.com/users/francoischalifour/starred{/owner}{/repo}",
      "subscriptions_url": "https://api.github.com/users/francoischalifour/subscriptions",
      "type": "User",
      "url": "https://api.github.com/users/francoischalifour",
      "user_view_type": "public"
    }
  },
  {
    "author_association": "CONTRIBUTOR",
    "body": "The link was fixed in the code. You can see the new documentation on the [Algolia website](https://www.algolia.com/doc/api-reference/widgets/autocomplete/js/).\r\n\r\nWe wrote a [guide for Angular InstantSearch](https://www.algolia.com/doc/guides/building-search-ui/resources/ui-and-ux-patterns/in-depth/autocomplete/angular/) to leverage this connector.",
    "created_at": "2019-03-14T15:34:18Z",
    "html_url": "https://github.com/algolia/instantsearch/issues/3307#issuecomment-472921929",
    "id": 472921929,
    "issue_url": "https://api.github.com/repos/algolia/instantsearch/issues/3307",
    "node_id": "MDEyOklzc3VlQ29tbWVudDQ3MjkyMTkyOQ==",
    "performed_via_github_app": null,
    "pin": null,
    "reactions": {
      "+1": 0,
      "-1": 0,
      "confused": 0,
      "eyes": 0,
      "heart": 0,
      "hooray": 0,
      "laugh": 0,
      "rocket": 0,
      "total_count": 0,
      "url": "https://api.github.com/repos/algolia/instantsearch/issues/comments/472921929/reactions"
    },
    "updated_at": "2019-03-14T15:34:18Z",
    "url": "https://api.github.com/repos/algolia/instantsearch/issues/comments/472921929",
    "user": {
      "avatar_url": "https://avatars.githubusercontent.com/u/6137112?v=4",
      "events_url": "https://api.github.com/users/francoischalifour/events{/privacy}",
      "followers_url": "https://api.github.com/users/francoischalifour/followers",
      "following_url": "https://api.github.com/users/francoischalifour/following{/other_user}",
      "gists_url": "https://api.github.com/users/francoischalifour/gists{/gist_id}",
      "gravatar_id": "",
      "html_url": "https://github.com/francoischalifour",
      "id": 6137112,
      "login": "francoischalifour",
      "node_id": "MDQ6VXNlcjYxMzcxMTI=",
      "organizations_url": "https://api.github.com/users/francoischalifour/orgs",
      "received_events_url": "https://api.github.com/users/francoischalifour/received_events",
      "repos_url": "https://api.github.com/users/francoischalifour/repos",
      "site_admin": false,
      "starred_url": "https://api.github.com/users/francoischalifour/starred{/owner}{/repo}",
      "subscriptions_url": "https://api.github.com/users/francoischalifour/subscriptions",
      "type": "User",
      "url": "https://api.github.com/users/francoischalifour",
      "user_view_type": "public"
    }
  }
]
