{
  "hash": "7d2838ed9",
  "author": "Haroen Viaene",
  "subject": "docs(stories): remove bindEvent from examples (#5448)",
  "body": "* fix(sendEvent):  correct types in template\r\n\r\nsendEvent is only passed in cases bindEvent is as well (hits, infinitehits), and this means  `?.` in the docs can be removed before sendEvent\r\n\r\n* make types pass\r\n\r\n* docs(stories): remove bindEvent from examples\r\n\r\nit doesn't work with `html`, so there's no point in continuing to have examples using it.\r\n\r\n* Update packages/instantsearch.js/stories/infinite-hits.stories.ts\r\n\r\n* Apply suggestions from code review\r\n\r\n* oh, it needs to be a function of course",
  "date": 1674582273,
  "longHash": "7d2838ed98668abb101cf90c57c3452f0db7b3e4"
}
