[
  {
    "author_association": "CONTRIBUTOR",
    "body": "Hi @attila-csaszar, the reproduction you sent doesn't actually execute on codesandbox, so it's not straightforward what you actually mean with the issue.\r\n\r\nNote that you can map over the individual items in the hierarchy if they are arrays: `{hit.hierarchy.lvl1.map((_, i) => <Highlight key={i} hit={hit} attribute={[\"hierarchy\", \"lvl1\", i]} />}`",
    "created_at": "2023-08-01T11:46:22Z",
    "html_url": "https://github.com/algolia/instantsearch/issues/5791#issuecomment-1660149330",
    "id": 1660149330,
    "issue_url": "https://api.github.com/repos/algolia/instantsearch/issues/5791",
    "node_id": "IC_kwDOAlnbOs5i895S",
    "performed_via_github_app": null,
    "pin": null,
    "reactions": {
      "+1": 0,
      "-1": 0,
      "confused": 0,
      "eyes": 0,
      "heart": 0,
      "hooray": 1,
      "laugh": 0,
      "rocket": 0,
      "total_count": 1,
      "url": "https://api.github.com/repos/algolia/instantsearch/issues/comments/1660149330/reactions"
    },
    "updated_at": "2023-08-01T11:46:22Z",
    "url": "https://api.github.com/repos/algolia/instantsearch/issues/comments/1660149330",
    "user": {
      "avatar_url": "https://avatars.githubusercontent.com/u/6270048?v=4",
      "events_url": "https://api.github.com/users/Haroenv/events{/privacy}",
      "followers_url": "https://api.github.com/users/Haroenv/followers",
      "following_url": "https://api.github.com/users/Haroenv/following{/other_user}",
      "gists_url": "https://api.github.com/users/Haroenv/gists{/gist_id}",
      "gravatar_id": "",
      "html_url": "https://github.com/Haroenv",
      "id": 6270048,
      "login": "Haroenv",
      "node_id": "MDQ6VXNlcjYyNzAwNDg=",
      "organizations_url": "https://api.github.com/users/Haroenv/orgs",
      "received_events_url": "https://api.github.com/users/Haroenv/received_events",
      "repos_url": "https://api.github.com/users/Haroenv/repos",
      "site_admin": false,
      "starred_url": "https://api.github.com/users/Haroenv/starred{/owner}{/repo}",
      "subscriptions_url": "https://api.github.com/users/Haroenv/subscriptions",
      "type": "User",
      "url": "https://api.github.com/users/Haroenv",
      "user_view_type": "public"
    }
  },
  {
    "author_association": "NONE",
    "body": "Hey, thanks for the quick reply.\r\nI know it does not execute there. I am using the Docusaurus static html generator, and there the app works as a single .jsx page, I do not need any extra files other than the css.\r\n\r\nI am a little new to all this, so could you elaborate on mapping over the items in the hierarchy? What does this do exactly? Where should I put this in my code?\r\nI tried and failed to find any info about this anywhere.\r\nThanks in advance.",
    "created_at": "2023-08-02T08:45:37Z",
    "html_url": "https://github.com/algolia/instantsearch/issues/5791#issuecomment-1661783599",
    "id": 1661783599,
    "issue_url": "https://api.github.com/repos/algolia/instantsearch/issues/5791",
    "node_id": "IC_kwDOAlnbOs5jDM4v",
    "performed_via_github_app": null,
    "pin": null,
    "reactions": {
      "+1": 0,
      "-1": 0,
      "confused": 0,
      "eyes": 0,
      "heart": 0,
      "hooray": 0,
      "laugh": 0,
      "rocket": 0,
      "total_count": 0,
      "url": "https://api.github.com/repos/algolia/instantsearch/issues/comments/1661783599/reactions"
    },
    "updated_at": "2023-08-02T08:46:05Z",
    "url": "https://api.github.com/repos/algolia/instantsearch/issues/comments/1661783599",
    "user": {
      "avatar_url": "https://avatars.githubusercontent.com/u/104343999?v=4",
      "events_url": "https://api.github.com/users/attila-csaszar/events{/privacy}",
      "followers_url": "https://api.github.com/users/attila-csaszar/followers",
      "following_url": "https://api.github.com/users/attila-csaszar/following{/other_user}",
      "gists_url": "https://api.github.com/users/attila-csaszar/gists{/gist_id}",
      "gravatar_id": "",
      "html_url": "https://github.com/attila-csaszar",
      "id": 104343999,
      "login": "attila-csaszar",
      "node_id": "U_kgDOBjgpvw",
      "organizations_url": "https://api.github.com/users/attila-csaszar/orgs",
      "received_events_url": "https://api.github.com/users/attila-csaszar/received_events",
      "repos_url": "https://api.github.com/users/attila-csaszar/repos",
      "site_admin": false,
      "starred_url": "https://api.github.com/users/attila-csaszar/starred{/owner}{/repo}",
      "subscriptions_url": "https://api.github.com/users/attila-csaszar/subscriptions",
      "type": "User",
      "url": "https://api.github.com/users/attila-csaszar",
      "user_view_type": "public"
    }
  },
  {
    "author_association": "CONTRIBUTOR",
    "body": "If `hit.hierarchy.lvl1` is an array, and you want to display every item of the array, what you do is you replace:\r\n\r\n```jsx\r\n<Highlight hit={hit} attribute=\"hierarchy.lvl1\" />\r\n```\r\n\r\nwith\r\n\r\n```jsx\r\n{hit.hierarchy.lvl1.map((_, i) => <Highlight key={i} hit={hit} attribute={[\"hierarchy\", \"lvl1\", i]} />}\r\n```\r\n\r\nso that you are looping over the items in the array, and create a highlight for each of the items in the array, this is similar to doing `hierarchy.lvl1[i]`\r\n ",
    "created_at": "2023-08-02T09:01:35Z",
    "html_url": "https://github.com/algolia/instantsearch/issues/5791#issuecomment-1661818749",
    "id": 1661818749,
    "issue_url": "https://api.github.com/repos/algolia/instantsearch/issues/5791",
    "node_id": "IC_kwDOAlnbOs5jDVd9",
    "performed_via_github_app": null,
    "pin": null,
    "reactions": {
      "+1": 0,
      "-1": 0,
      "confused": 0,
      "eyes": 0,
      "heart": 0,
      "hooray": 0,
      "laugh": 0,
      "rocket": 0,
      "total_count": 0,
      "url": "https://api.github.com/repos/algolia/instantsearch/issues/comments/1661818749/reactions"
    },
    "updated_at": "2023-08-02T09:01:35Z",
    "url": "https://api.github.com/repos/algolia/instantsearch/issues/comments/1661818749",
    "user": {
      "avatar_url": "https://avatars.githubusercontent.com/u/6270048?v=4",
      "events_url": "https://api.github.com/users/Haroenv/events{/privacy}",
      "followers_url": "https://api.github.com/users/Haroenv/followers",
      "following_url": "https://api.github.com/users/Haroenv/following{/other_user}",
      "gists_url": "https://api.github.com/users/Haroenv/gists{/gist_id}",
      "gravatar_id": "",
      "html_url": "https://github.com/Haroenv",
      "id": 6270048,
      "login": "Haroenv",
      "node_id": "MDQ6VXNlcjYyNzAwNDg=",
      "organizations_url": "https://api.github.com/users/Haroenv/orgs",
      "received_events_url": "https://api.github.com/users/Haroenv/received_events",
      "repos_url": "https://api.github.com/users/Haroenv/repos",
      "site_admin": false,
      "starred_url": "https://api.github.com/users/Haroenv/starred{/owner}{/repo}",
      "subscriptions_url": "https://api.github.com/users/Haroenv/subscriptions",
      "type": "User",
      "url": "https://api.github.com/users/Haroenv",
      "user_view_type": "public"
    }
  }
]
