[
  {
    "author_association": "CONTRIBUTOR",
    "body": "Hmm, I think we still need the `width: 100%` on the search box.\n\nie. we still need some specific styling of the widget for the documentation that are not part of the `instantsearch.css` file, and I feel we should keep them in a separate file than the rest of the CSS for the docs\n",
    "created_at": "2015-11-12T10:14:14Z",
    "html_url": "https://github.com/algolia/instantsearch/pull/554#issuecomment-156058003",
    "id": 156058003,
    "issue_url": "https://api.github.com/repos/algolia/instantsearch/issues/554",
    "node_id": "MDEyOklzc3VlQ29tbWVudDE1NjA1ODAwMw==",
    "performed_via_github_app": null,
    "pin": null,
    "reactions": {
      "+1": 0,
      "-1": 0,
      "confused": 0,
      "eyes": 0,
      "heart": 0,
      "hooray": 0,
      "laugh": 0,
      "rocket": 0,
      "total_count": 0,
      "url": "https://api.github.com/repos/algolia/instantsearch/issues/comments/156058003/reactions"
    },
    "updated_at": "2015-11-12T10:14:14Z",
    "url": "https://api.github.com/repos/algolia/instantsearch/issues/comments/156058003",
    "user": {
      "avatar_url": "https://avatars.githubusercontent.com/u/283419?v=4",
      "events_url": "https://api.github.com/users/pixelastic/events{/privacy}",
      "followers_url": "https://api.github.com/users/pixelastic/followers",
      "following_url": "https://api.github.com/users/pixelastic/following{/other_user}",
      "gists_url": "https://api.github.com/users/pixelastic/gists{/gist_id}",
      "gravatar_id": "",
      "html_url": "https://github.com/pixelastic",
      "id": 283419,
      "login": "pixelastic",
      "node_id": "MDQ6VXNlcjI4MzQxOQ==",
      "organizations_url": "https://api.github.com/users/pixelastic/orgs",
      "received_events_url": "https://api.github.com/users/pixelastic/received_events",
      "repos_url": "https://api.github.com/users/pixelastic/repos",
      "site_admin": false,
      "starred_url": "https://api.github.com/users/pixelastic/starred{/owner}{/repo}",
      "subscriptions_url": "https://api.github.com/users/pixelastic/subscriptions",
      "type": "User",
      "url": "https://api.github.com/users/pixelastic",
      "user_view_type": "public"
    }
  },
  {
    "author_association": "CONTRIBUTOR",
    "body": "> Hmm, I think we still need the width: 100% on the search box.\n\nAh yes true, will do.\n",
    "created_at": "2015-11-12T13:16:18Z",
    "html_url": "https://github.com/algolia/instantsearch/pull/554#issuecomment-156099960",
    "id": 156099960,
    "issue_url": "https://api.github.com/repos/algolia/instantsearch/issues/554",
    "node_id": "MDEyOklzc3VlQ29tbWVudDE1NjA5OTk2MA==",
    "performed_via_github_app": null,
    "pin": null,
    "reactions": {
      "+1": 0,
      "-1": 0,
      "confused": 0,
      "eyes": 0,
      "heart": 0,
      "hooray": 0,
      "laugh": 0,
      "rocket": 0,
      "total_count": 0,
      "url": "https://api.github.com/repos/algolia/instantsearch/issues/comments/156099960/reactions"
    },
    "updated_at": "2015-11-12T13:16:18Z",
    "url": "https://api.github.com/repos/algolia/instantsearch/issues/comments/156099960",
    "user": {
      "avatar_url": "https://avatars.githubusercontent.com/u/29529?v=4",
      "events_url": "https://api.github.com/users/redox/events{/privacy}",
      "followers_url": "https://api.github.com/users/redox/followers",
      "following_url": "https://api.github.com/users/redox/following{/other_user}",
      "gists_url": "https://api.github.com/users/redox/gists{/gist_id}",
      "gravatar_id": "",
      "html_url": "https://github.com/redox",
      "id": 29529,
      "login": "redox",
      "node_id": "MDQ6VXNlcjI5NTI5",
      "organizations_url": "https://api.github.com/users/redox/orgs",
      "received_events_url": "https://api.github.com/users/redox/received_events",
      "repos_url": "https://api.github.com/users/redox/repos",
      "site_admin": false,
      "starred_url": "https://api.github.com/users/redox/starred{/owner}{/repo}",
      "subscriptions_url": "https://api.github.com/users/redox/subscriptions",
      "type": "User",
      "url": "https://api.github.com/users/redox",
      "user_view_type": "public"
    }
  }
]
