[
  {
    "author_association": "CONTRIBUTOR",
    "body": "Why don't we do : \n\n``` js\nvar stylesheet = document.createElement('link');\nstylesheet.href = 'http://' + window.location.hostname +':8080/instantsearch.css';\ndocument.body.appendChild(stylesheet);\n```\n",
    "created_at": "2015-11-17T12:57:24Z",
    "html_url": "https://github.com/algolia/instantsearch/pull/628#issuecomment-157364090",
    "id": 157364090,
    "issue_url": "https://api.github.com/repos/algolia/instantsearch/issues/628",
    "node_id": "MDEyOklzc3VlQ29tbWVudDE1NzM2NDA5MA==",
    "performed_via_github_app": null,
    "pin": null,
    "reactions": {
      "+1": 0,
      "-1": 0,
      "confused": 0,
      "eyes": 0,
      "heart": 0,
      "hooray": 0,
      "laugh": 0,
      "rocket": 0,
      "total_count": 0,
      "url": "https://api.github.com/repos/algolia/instantsearch/issues/comments/157364090/reactions"
    },
    "updated_at": "2015-11-17T12:57:24Z",
    "url": "https://api.github.com/repos/algolia/instantsearch/issues/comments/157364090",
    "user": {
      "avatar_url": "https://avatars.githubusercontent.com/u/393765?v=4",
      "events_url": "https://api.github.com/users/bobylito/events{/privacy}",
      "followers_url": "https://api.github.com/users/bobylito/followers",
      "following_url": "https://api.github.com/users/bobylito/following{/other_user}",
      "gists_url": "https://api.github.com/users/bobylito/gists{/gist_id}",
      "gravatar_id": "",
      "html_url": "https://github.com/bobylito",
      "id": 393765,
      "login": "bobylito",
      "node_id": "MDQ6VXNlcjM5Mzc2NQ==",
      "organizations_url": "https://api.github.com/users/bobylito/orgs",
      "received_events_url": "https://api.github.com/users/bobylito/received_events",
      "repos_url": "https://api.github.com/users/bobylito/repos",
      "site_admin": false,
      "starred_url": "https://api.github.com/users/bobylito/starred{/owner}{/repo}",
      "subscriptions_url": "https://api.github.com/users/bobylito/subscriptions",
      "type": "User",
      "url": "https://api.github.com/users/bobylito",
      "user_view_type": "public"
    }
  },
  {
    "author_association": "CONTRIBUTOR",
    "body": "Otherwise LGTM\n",
    "created_at": "2015-11-17T12:59:19Z",
    "html_url": "https://github.com/algolia/instantsearch/pull/628#issuecomment-157364384",
    "id": 157364384,
    "issue_url": "https://api.github.com/repos/algolia/instantsearch/issues/628",
    "node_id": "MDEyOklzc3VlQ29tbWVudDE1NzM2NDM4NA==",
    "performed_via_github_app": null,
    "pin": null,
    "reactions": {
      "+1": 0,
      "-1": 0,
      "confused": 0,
      "eyes": 0,
      "heart": 0,
      "hooray": 0,
      "laugh": 0,
      "rocket": 0,
      "total_count": 0,
      "url": "https://api.github.com/repos/algolia/instantsearch/issues/comments/157364384/reactions"
    },
    "updated_at": "2015-11-17T12:59:19Z",
    "url": "https://api.github.com/repos/algolia/instantsearch/issues/comments/157364384",
    "user": {
      "avatar_url": "https://avatars.githubusercontent.com/u/393765?v=4",
      "events_url": "https://api.github.com/users/bobylito/events{/privacy}",
      "followers_url": "https://api.github.com/users/bobylito/followers",
      "following_url": "https://api.github.com/users/bobylito/following{/other_user}",
      "gists_url": "https://api.github.com/users/bobylito/gists{/gist_id}",
      "gravatar_id": "",
      "html_url": "https://github.com/bobylito",
      "id": 393765,
      "login": "bobylito",
      "node_id": "MDQ6VXNlcjM5Mzc2NQ==",
      "organizations_url": "https://api.github.com/users/bobylito/orgs",
      "received_events_url": "https://api.github.com/users/bobylito/received_events",
      "repos_url": "https://api.github.com/users/bobylito/repos",
      "site_admin": false,
      "starred_url": "https://api.github.com/users/bobylito/starred{/owner}{/repo}",
      "subscriptions_url": "https://api.github.com/users/bobylito/subscriptions",
      "type": "User",
      "url": "https://api.github.com/users/bobylito",
      "user_view_type": "public"
    }
  },
  {
    "author_association": "CONTRIBUTOR",
    "body": "By doing so, the script/style will be loaded after all the other pending requests. This is not big deal for CSS, but will break JS. So I used the same method for both types, because it was easier.\n",
    "created_at": "2015-11-17T13:02:41Z",
    "html_url": "https://github.com/algolia/instantsearch/pull/628#issuecomment-157364962",
    "id": 157364962,
    "issue_url": "https://api.github.com/repos/algolia/instantsearch/issues/628",
    "node_id": "MDEyOklzc3VlQ29tbWVudDE1NzM2NDk2Mg==",
    "performed_via_github_app": null,
    "pin": null,
    "reactions": {
      "+1": 0,
      "-1": 0,
      "confused": 0,
      "eyes": 0,
      "heart": 0,
      "hooray": 0,
      "laugh": 0,
      "rocket": 0,
      "total_count": 0,
      "url": "https://api.github.com/repos/algolia/instantsearch/issues/comments/157364962/reactions"
    },
    "updated_at": "2015-11-17T13:02:41Z",
    "url": "https://api.github.com/repos/algolia/instantsearch/issues/comments/157364962",
    "user": {
      "avatar_url": "https://avatars.githubusercontent.com/u/283419?v=4",
      "events_url": "https://api.github.com/users/pixelastic/events{/privacy}",
      "followers_url": "https://api.github.com/users/pixelastic/followers",
      "following_url": "https://api.github.com/users/pixelastic/following{/other_user}",
      "gists_url": "https://api.github.com/users/pixelastic/gists{/gist_id}",
      "gravatar_id": "",
      "html_url": "https://github.com/pixelastic",
      "id": 283419,
      "login": "pixelastic",
      "node_id": "MDQ6VXNlcjI4MzQxOQ==",
      "organizations_url": "https://api.github.com/users/pixelastic/orgs",
      "received_events_url": "https://api.github.com/users/pixelastic/received_events",
      "repos_url": "https://api.github.com/users/pixelastic/repos",
      "site_admin": false,
      "starred_url": "https://api.github.com/users/pixelastic/starred{/owner}{/repo}",
      "subscriptions_url": "https://api.github.com/users/pixelastic/subscriptions",
      "type": "User",
      "url": "https://api.github.com/users/pixelastic",
      "user_view_type": "public"
    }
  },
  {
    "author_association": "CONTRIBUTOR",
    "body": "Yep good good ;)\n",
    "created_at": "2015-11-17T13:13:13Z",
    "html_url": "https://github.com/algolia/instantsearch/pull/628#issuecomment-157367394",
    "id": 157367394,
    "issue_url": "https://api.github.com/repos/algolia/instantsearch/issues/628",
    "node_id": "MDEyOklzc3VlQ29tbWVudDE1NzM2NzM5NA==",
    "performed_via_github_app": null,
    "pin": null,
    "reactions": {
      "+1": 0,
      "-1": 0,
      "confused": 0,
      "eyes": 0,
      "heart": 0,
      "hooray": 0,
      "laugh": 0,
      "rocket": 0,
      "total_count": 0,
      "url": "https://api.github.com/repos/algolia/instantsearch/issues/comments/157367394/reactions"
    },
    "updated_at": "2015-11-17T13:13:13Z",
    "url": "https://api.github.com/repos/algolia/instantsearch/issues/comments/157367394",
    "user": {
      "avatar_url": "https://avatars.githubusercontent.com/u/393765?v=4",
      "events_url": "https://api.github.com/users/bobylito/events{/privacy}",
      "followers_url": "https://api.github.com/users/bobylito/followers",
      "following_url": "https://api.github.com/users/bobylito/following{/other_user}",
      "gists_url": "https://api.github.com/users/bobylito/gists{/gist_id}",
      "gravatar_id": "",
      "html_url": "https://github.com/bobylito",
      "id": 393765,
      "login": "bobylito",
      "node_id": "MDQ6VXNlcjM5Mzc2NQ==",
      "organizations_url": "https://api.github.com/users/bobylito/orgs",
      "received_events_url": "https://api.github.com/users/bobylito/received_events",
      "repos_url": "https://api.github.com/users/bobylito/repos",
      "site_admin": false,
      "starred_url": "https://api.github.com/users/bobylito/starred{/owner}{/repo}",
      "subscriptions_url": "https://api.github.com/users/bobylito/subscriptions",
      "type": "User",
      "url": "https://api.github.com/users/bobylito",
      "user_view_type": "public"
    }
  }
]
